setup.py
spinnaker_proxy/__init__.py
spinnaker_proxy/spinnaker_proxy.py
spinnaker_proxy.egg-info/PKG-INFO
spinnaker_proxy.egg-info/SOURCES.txt
spinnaker_proxy.egg-info/dependency_links.txt
spinnaker_proxy.egg-info/requires.txt
spinnaker_proxy.egg-info/top_level.txt