Metadata-Version: 1.0
Name: spinnaker-proxy
Version: 2.0.3
Summary: A proxy-server for SpiNNaker systems.
Home-page: https://github.com/project-rig/spinnaker_proxy
Author: Jonathan Heathcote
Author-email: UNKNOWN
License: GPLv2
Platform: UNKNOWN
